MANIFEST.in
README.txt
setup.py
collective/.DS_Store
collective/__init__.py
collective/__init__.pyc
collective.js.supersized.egg-info/PKG-INFO
collective.js.supersized.egg-info/SOURCES.txt
collective.js.supersized.egg-info/dependency_links.txt
collective.js.supersized.egg-info/entry_points.txt
collective.js.supersized.egg-info/namespace_packages.txt
collective.js.supersized.egg-info/not-zip-safe
collective.js.supersized.egg-info/requires.txt
collective.js.supersized.egg-info/top_level.txt
collective/js/.DS_Store
collective/js/__init__.py
collective/js/__init__.pyc
collective/js/supersized/.DS_Store
collective/js/supersized/README
collective/js/supersized/__init__.py
collective/js/supersized/__init__.pyc
collective/js/supersized/behavior.py
collective/js/supersized/behavior.pyc
collective/js/supersized/behaviors.zcml
collective/js/supersized/configure.zcml
collective/js/supersized/interfaces.py
collective/js/supersized/interfaces.pyc
collective/js/supersized/upgrades.py
collective/js/supersized/upgrades.pyc
collective/js/supersized/vocabulary.py
collective/js/supersized/vocabulary.pyc
collective/js/supersized/browser/.DS_Store
collective/js/supersized/browser/__init__.py
collective/js/supersized/browser/__init__.pyc
collective/js/supersized/browser/configure.zcml
collective/js/supersized/browser/supersized.pt
collective/js/supersized/browser/viewlet.pt
collective/js/supersized/browser/viewlets.py
collective/js/supersized/browser/viewlets.pyc
collective/js/supersized/browser/views.py
collective/js/supersized/browser/views.pyc
collective/js/supersized/profiles/.DS_Store
collective/js/supersized/profiles/default/browserlayer.xml
collective/js/supersized/profiles/default/cssregistry.xml
collective/js/supersized/profiles/default/jsregistry.xml
collective/js/supersized/profiles/default/metadata.xml
collective/js/supersized/profiles/default/registry.xml
collective/js/supersized/profiles/default/types.xml
collective/js/supersized/profiles/default/viewlets.xml
collective/js/supersized/profiles/default/types/News_Item.xml
collective/js/supersized/profiles/to_11/browserlayer.xml
collective/js/supersized/profiles/to_11/jsregistry.xml
collective/js/supersized/profiles/to_11/metadata.xml
collective/js/supersized/profiles/to_11/registry.xml
collective/js/supersized/profiles/to_11/viewlets.xml
collective/js/supersized/profiles/uninstall/browserlayer.xml
