Metadata-Version: 1.0
Name: collective.js.supersized
Version: 0.4.4
Summary: JQuery Supersized for Plone
Home-page: http://github.com/collective/collective.js.supersized
Author: Espen Moe-Nillssen
Author-email: espen@medialog.no
License: GPL
Keywords: JQuery Supersized plugin plone resource
Platform: UNKNOWN
Classifier: Development Status :: 3 - Alpha
Classifier: Environment :: Web Environment
Classifier: Framework :: Plone
Classifier: Framework :: Plone :: 4.1
Classifier: Framework :: Plone :: 4.2
Classifier: Framework :: Plone :: 4.3
Classifier: Framework :: Zope2
Classifier: Framework :: Zope3
Classifier: Intended Audience :: Developers
Classifier: Intended Audience :: End Users/Desktop
Classifier: Operating System :: OS Independent
Classifier: Programming Language :: Python
Classifier: Programming Language :: Python :: 2.6
Classifier: Programming Language :: Python :: 2.7
Classifier: Topic :: Internet
Classifier: Topic :: Software Development :: Libraries :: Python Modules
